wss_py/__init__.py
wss_py/brain.py
wss_py/console.py
wss_py/direction.py
wss_py/event.py
wss_py/game.py
wss_py/item.py
wss_py/listener.py
wss_py/main.py
wss_py/map.py
wss_py/message_board.py
wss_py/player.py
wss_py/terrain.py
wss_py/text_renderable.py
wss_py/vision.py
wss_py-0.0.2.dist-info/METADATA
wss_py-0.0.2.dist-info/WHEEL
wss_py-0.0.2.dist-info/entry_points.txt
wss_py-0.0.2.dist-info/licenses/LICENSE
wss_py-0.0.2.dist-info/RECORD
