Metadata-Version: 2.4
Name: wss_py
Version: 0.0.2
Summary: A self-playing terminal UI game.
Author: Kenji Longid, Chris Iang, Makar Dzerushau, Youngchan Kim
License: MIT
License-File: LICENSE
Classifier: Operating System :: OS Independent
Classifier: Programming Language :: Python :: 3
Requires-Python: >=3.9
Requires-Dist: noise
Requires-Dist: numpy
Requires-Dist: rich
